quastt_show/__init__.py
quastt_show/game.py
quastt_show/logger.py
quastt_show/monitoring.py
quastt_show/nothing.py
quastt_show/resources.py
quastt_show-0.3.37.dist-info/METADATA
quastt_show-0.3.37.dist-info/WHEEL
quastt_show-0.3.37.dist-info/entry_points.txt
quastt_show-0.3.37.dist-info/top_level.txt
quastt_show-0.3.37.dist-info/RECORD
