Metadata-Version: 2.4
Name: quastt_show
Version: 0.3.37
Summary: Useful tools for monitoring,tracking,learning from mistakes.Just check our docs: https://quastt.com/
Author: RVA
Requires-Python: >=3.7
Requires-Dist: requests
Dynamic: author
Dynamic: requires-dist
Dynamic: requires-python
Dynamic: summary
